ckanext_privatedatasets-0.4-py3.7-nspkg.pth
ckanext/privatedatasets/actions.py
ckanext/privatedatasets/auth.py
ckanext/privatedatasets/constants.py
ckanext/privatedatasets/converters_validators.py
ckanext/privatedatasets/db.py
ckanext/privatedatasets/helpers.py
ckanext/privatedatasets/plugin.py
ckanext/privatedatasets/views.py
ckanext/privatedatasets/controllers/__init__.py
ckanext/privatedatasets/controllers/ui_controller.py
ckanext/privatedatasets/fanstatic/allowed_users.js
ckanext/privatedatasets/fanstatic/custom.css
ckanext/privatedatasets/parsers/__init__.py
ckanext/privatedatasets/parsers/fiware.py
ckanext/privatedatasets/templates/package/snippets/package_basic_fields.html
ckanext/privatedatasets/templates/snippets/acquire_button.html
ckanext/privatedatasets/templates/snippets/package_item.html
ckanext/privatedatasets/templates/user/dashboard.html
ckanext/privatedatasets/templates/user/dashboard_acquired.html
ckanext/privatedatasets/templates/user/new
ckanext/privatedatasets/templates/user/old
ckanext/privatedatasets/templates_2.8/package/snippets/package_basic_fields.html
ckanext/privatedatasets/templates_2.8/snippets/acquire_button.html
ckanext/privatedatasets/templates_2.8/snippets/package_item.html
ckanext/privatedatasets/templates_2.8/user/dashboard.html
ckanext/privatedatasets/templates_2.8/user/dashboard_acquired.html
ckanext/privatedatasets/tests/__init__.py
ckanext/privatedatasets/tests/test_actions.py
ckanext/privatedatasets/tests/test_auth.py
ckanext/privatedatasets/tests/test_controller_ui.py
ckanext/privatedatasets/tests/test_converters_validators.py
ckanext/privatedatasets/tests/test_db.py
ckanext/privatedatasets/tests/test_fiware_parser.py
ckanext/privatedatasets/tests/test_helpers.py
ckanext/privatedatasets/tests/test_plugin.py
ckanext/privatedatasets/tests/test_selenium.py
ckanext/privatedatasets/tests/test_views.py
ckanext_privatedatasets-0.4.dist-info/METADATA
ckanext_privatedatasets-0.4.dist-info/RECORD
ckanext_privatedatasets-0.4.dist-info/WHEEL
ckanext_privatedatasets-0.4.dist-info/entry_points.txt
ckanext_privatedatasets-0.4.dist-info/namespace_packages.txt
ckanext_privatedatasets-0.4.dist-info/top_level.txt
