Metadata-Version: 2.1
Name: ckanext-privatedatasets
Version: 0.4
Summary: CKAN Extension - Private Datasets
Home-page: https://conwet.fi.upm.es
Author: Aitor Magan
Author-email: amagan@conwet.com
License: UNKNOWN
Download-URL: https://github.com/conwetlab/ckanext-privatedatasets/tarball/v0.4
Keywords: ckan,private,datasets
Platform: UNKNOWN
